score.netfs-0.5.2-py3.4-nspkg.pth
score/netfs/__init__.py
score/netfs/_connection.py
score/netfs/_exceptions.py
score/netfs/_init.py
score/netfs/cli.py
score/netfs/constants.py
score/netfs/server.py
score/netfs/proxy/__init__.py
score/netfs/proxy/backend.py
score/netfs/proxy/frontend.py
score/netfs/proxy/operation/__init__.py
score/netfs/proxy/operation/base.py
score/netfs/proxy/operation/commit.py
score/netfs/proxy/operation/download.py
score/netfs/proxy/operation/prepare.py
score/netfs/proxy/operation/upload.py
score.netfs-0.5.2.dist-info/DESCRIPTION.rst
score.netfs-0.5.2.dist-info/METADATA
score.netfs-0.5.2.dist-info/RECORD
score.netfs-0.5.2.dist-info/WHEEL
score.netfs-0.5.2.dist-info/entry_points.txt
score.netfs-0.5.2.dist-info/metadata.json
score.netfs-0.5.2.dist-info/namespace_packages.txt
score.netfs-0.5.2.dist-info/top_level.txt
